bluefin_pro_api_client/__init__.py
bluefin_pro_api_client/api_client.py
bluefin_pro_api_client/api_response.py
bluefin_pro_api_client/configuration.py
bluefin_pro_api_client/exceptions.py
bluefin_pro_api_client/py.typed
bluefin_pro_api_client/rest.py
bluefin_pro_api_client/api/__init__.py
bluefin_pro_api_client/api/account_data_api.py
bluefin_pro_api_client/api/auth_api.py
bluefin_pro_api_client/api/exchange_api.py
bluefin_pro_api_client/api/streams_api.py
bluefin_pro_api_client/api/trade_api.py
bluefin_pro_api_client/models/__init__.py
bluefin_pro_api_client/models/account.py
bluefin_pro_api_client/models/account_data_stream.py
bluefin_pro_api_client/models/account_event_reason.py
bluefin_pro_api_client/models/account_event_type.py
bluefin_pro_api_client/models/account_market_preference.py
bluefin_pro_api_client/models/account_order_update.py
bluefin_pro_api_client/models/account_position_leverage_update_request.py
bluefin_pro_api_client/models/account_position_leverage_update_request_signed_fields.py
bluefin_pro_api_client/models/account_position_update.py
bluefin_pro_api_client/models/account_preference.py
bluefin_pro_api_client/models/account_stream_message.py
bluefin_pro_api_client/models/account_stream_message_payload.py
bluefin_pro_api_client/models/account_subscription_message.py
bluefin_pro_api_client/models/account_trade_update.py
bluefin_pro_api_client/models/account_transaction_update.py
bluefin_pro_api_client/models/account_update.py
bluefin_pro_api_client/models/active_order_update.py
bluefin_pro_api_client/models/asset.py
bluefin_pro_api_client/models/asset1.py
bluefin_pro_api_client/models/asset2.py
bluefin_pro_api_client/models/cancel_orders_request.py
bluefin_pro_api_client/models/candle_price_type.py
bluefin_pro_api_client/models/candlestick_interval.py
bluefin_pro_api_client/models/candlestick_price_type.py
bluefin_pro_api_client/models/candlestick_stream.py
bluefin_pro_api_client/models/candlestick_update.py
bluefin_pro_api_client-1.0.0.dist-info/METADATA
bluefin_pro_api_client-1.0.0.dist-info/WHEEL
bluefin_pro_api_client-1.0.0.dist-info/top_level.txt
bluefin_pro_api_client-1.0.0.dist-info/RECORD
